AudioAlchemist/__init__.py
AudioAlchemist/audio_alchemist.py
AudioAlchemist-0.8.0.dist-info/METADATA
AudioAlchemist-0.8.0.dist-info/WHEEL
AudioAlchemist-0.8.0.dist-info/top_level.txt
AudioAlchemist-0.8.0.dist-info/RECORD
