Metadata-Version: 2.1
Name: AudioAlchemist
Version: 0.8.0
Summary: Convert all files directly under the directory to any music file.
Home-page: https://github.com/Ryomo0797/AudioAlchemist.git
Download-URL: https://github.com/Ryomo0797/AudioAlchemist.git
Author: Kohki Suto
Author-email: s2222019@stu.musashino-u.ac.jp
Maintainer: Kohki Suto
Maintainer-email: s2222019@stu.musashino-u.ac.jp
License: MIT
Keywords: audio,pydub,glob,mp3,wav,flac,m4a,audio_convert,converter,audio_converter
Classifier: License :: OSI Approved :: MIT License
Classifier: Programming Language :: Python :: 3.6
Requires-Dist: pydub >=0.25.1
Requires-Dist: ffmpeg >=1.4
